{
    "data": {
        "isEnd": true,
        "list": [
            {
                "startTime": 1477030972,
                "tagLink1": "",
                "tagLink2": "",
                "tag2": "",
                "title": "\u5E05\u6C14\u53CC\u80A9\u5305",
                "tagLink3": "",
                "tag3": "",
                "acm": "3.mce.2_10_1854g.9439.0.pTuq64sDy0Q.m_189916_11228",
                "description": "\u4E24\u6839\u5E26\u5B50\u7B80\u76F4\u662F\u51CF\u9F84\u7684\u79D8\u7C4D\uFF0C\u4E0D\u7BA1\u662F\u80CC\u5E26\u88E4\u8FD8\u662F\u53CC\u80A9\u5305\uFF01",
                "link": "http\u003A\u002F\u002Fitem.meilishuo.com\u002Fh5\u002Fdetail\u002F1gktoq6\u003Fmt\u003D12.9439.r189916.11228\u0026acm\u003D3.mce.2_10_1854g.9439.0.pTuq64sDy0Q.m_189916_11228",
                "popularStar": "4",
                "image": "http\u003A\u002F\u002Fs6.mogucdn.com\u002Fp2\u002F161011\u002F1sx_1d6h9kj7fa2g1617dc75cdlllf6l1_400x400.jpg",
                "endTime": 0,
                "tag1": ""
            },
            {
                "startTime": 1477030974,
                "tagLink1": "mls\u003A\u002F\u002Fsearch\u002Fresult\u003Fkeyword\u003D\u5ED3\u5F62",
                "title": "\u957F\u8896\u5BBD\u677E\u5957\u5934\u6BDB\u8863",
                "tag2": "\u9488\u7EC7",
                "tagLink2": "mls\u003A\u002F\u002Fsearch\u002Fresult\u003Fkeyword\u003D\u9488\u7EC7",
                "tag3": "",
                "tagLink3": "",
                "acm": "3.mce.2_10_18552.9439.0.pTuq64sDy0R.m_189927_11228",
                "description": "\u4E2A\u6027\u5341\u8DB3\u7684\u62C9\u94FE\u8BBE\u8BA1\u70B9\uFF0C\u8BA9\u4EBA\u8FC7\u76EE\u4E0D\u5FD8\u7684\u5E05\u6C14\u611F\uFF0C\u7EDD\u5BF9\u662F\u4E00\u4EF6\u767E\u7A7F\u4E0D\u538C\u7684\u4F18\u8D28\u5355\u54C1\u54E6\uFF01",
                "link": "http\u003A\u002F\u002Fitem.meilishuo.com\u002Fh5\u002Fdetail\u002F1gkvo7w\u003Fmt\u003D12.9439.r189927.11228\u0026acm\u003D3.mce.2_10_18552.9439.0.pTuq64sDy0R.m_189927_11228",
                "image": "http\u003A\u002F\u002Fs8.mogucdn.com\u002Fp2\u002F160901\u002F1sd_3dg2g6i4d9k80he2a6k57312hf81f_400x400.jpg",
                "popularStar": "5",
                "endTime": 0,
                "tag1": "\u5ED3\u5F62"
            },
            {
                "startTime": 1477030973,
                "tagLink1": "mls\u003A\u002F\u002Fsearch\u002Fresult\u003Fkeyword\u003D\u5957\u88C5",
                "tagLink2": "mls\u003A\u002F\u002Fsearch\u002Fresult\u003Fkeyword\u003D\u9488\u7EC7\u88D9",
                "tag2": "\u9488\u7EC7\u88D9",
                "title": "\u4E03\u683C\u683C\u51AC\u5B63\u65B0\u6B3E\u5957\u88C5",
                "tagLink3": "",
                "tag3": "",
                "acm": "3.mce.2_10_1854w.9439.0.pTuq64sDy0S.m_189924_11228",
                "description": "\u8FD0\u52A8\u5370\u82B1\u536B\u8863\u002B\u4E2D\u957F\u6B3E\u5F00\u8869\u534A\u8EAB\u88D9\u65F6\u5C1A\u5957\u88C5\uFF0C\u5E2E\u4F60\u641E\u5B9A\u51AC\u5B63\u642D\u914D\uFF01",
                "link": "http\u003A\u002F\u002Fitem.meilishuo.com\u002Fh5\u002Fdetail\u002F1govo30\u003Fmt\u003D12.9439.r189924.11228\u0026acm\u003D3.mce.2_10_1854w.9439.0.pTuq64sDy0S.m_189924_11228",
                "popularStar": "4",
                "image": "http\u003A\u002F\u002Fs8.mogucdn.com\u002Fp2\u002F161009\u002F1sd_7687jb96jj1cl9k026f1da8ejh45h_400x400.png",
                "endTime": 0,
                "tag1": "\u5957\u88C5"
            },
            {
                "startTime": 1477030973,
                "tagLink1": "mls\u003A\u002F\u002Fsearch\u002Fresult\u003Fkeyword\u003D\u6D41\u82CF",
                "title": "\u5E73\u5E95\u6D41\u82CF\u53CA\u8E1D\u9774",
                "tag2": "",
                "tagLink2": "",
                "tag3": "",
                "tagLink3": "",
                "acm": "3.mce.2_10_1854i.9439.0.pTuq64sDy0T.m_189917_11228",
                "description": "\u6D41\u82CF\u77ED\u9774\u5E74\u5E74\u6D41\u884C\uFF0C\u4ECA\u5E74\u4E5F\u4E0D\u4F8B\u5916\u54E6\uFF01",
                "link": "http\u003A\u002F\u002Fitem.meilishuo.com\u002Fh5\u002Fdetail\u002F1glvsjm\u003Fmt\u003D12.9439.r189917.11228\u0026acm\u003D3.mce.2_10_1854i.9439.0.pTuq64sDy0T.m_189917_11228",
                "image": "http\u003A\u002F\u002Fs6.mogucdn.com\u002Fp2\u002F161010\u002F1sp_2lgl4h4i67ijhkalblk43dd5b1703_400x400.jpg",
                "popularStar": "5",
                "endTime": 0,
                "tag1": "\u6D41\u82CF"
            },
            {
                "startTime": 1477030973,
                "tagLink1": "mls\u003A\u002F\u002Fsearch\u002Fresult\u003Fkeyword\u003D\u590D\u53E4",
                "tagLink2": "",
                "tag2": "",
                "title": "\u590D\u53E4\u64E6\u8272\u5E73\u5E95\u77ED\u9774",
                "tagLink3": "",
                "tag3": "",
                "acm": "3.mce.2_10_1854o.9439.0.pTuq64sDy0U.m_189920_11228",
                "description": "\u4E00\u6B3E\u4E0A\u811A\u9177\u9177\u7684\u5E73\u5E95\u9774\uFF0C\u9774\u5B50\u7684\u5B63\u8282\u5230\u4E86\uFF0C\u8FD9\u6B3E\u9774\u5B50\u9002\u5408\u4F60\uFF01",
                "link": "http\u003A\u002F\u002Fitem.meilishuo.com\u002Fh5\u002Fdetail\u002F1glxftm\u003Fmt\u003D12.9439.r189920.11228\u0026acm\u003D3.mce.2_10_1854o.9439.0.pTuq64sDy0U.m_189920_11228",
                "popularStar": "5",
                "image": "http\u003A\u002F\u002Fs7.mogucdn.com\u002Fp2\u002F161009\u002F1sp_016klh45i36jiige1ee7e6bi7872a_400x400.jpg",
                "endTime": 0,
                "tag1": "\u590D\u53E4"
            },
            {
                "tags": "\u7F57\u9A6C\u978B\u0023\u51C9\u978B\u0023TOPSHOP",
                "startTime": 1466154319,
                "title": "TOPSHOP\u6D45\u68D5\u8272\u5E73\u5E95\u7F57\u9A6C\u51C9\u978B",
                "acm": "3.mce.2_10_14ip6.5514.0.pTuq64sDy0V.m_105401_11228",
                "description": "\u6BD4\u590F\u5929\u8FD8\u70ED\u7684\u7F57\u9A6C\u978B\uFF0C\u878D\u5165\u7ED1\u5E26\u5143\u7D20\u3002\u8212\u9002\u51C9\u723D\u8FD8\u80FD\u8F7B\u677E\u51F9\u9020\u578B\uFF0C\u4F60\u8BF4\u8981\u4E0D\u8981\uFF1F",
                "link": "http\u003A\u002F\u002Fsgitem.meilishuo.com\u002Fsgdetail\u002F650500026\u003Fmt\u003D12.5514.r105401.11228\u0026acm\u003D3.mce.2_10_14ip6.5514.0.pTuq64sDy0V.m_105401_11228",
                "popularStar": "5",
                "image": "http\u003A\u002F\u002Fs8.mogucdn.com\u002Fp1\u002F160511\u002F1vh_ifqtozlemzrgenjxhazdambqgyyde_320x320.png",
                "endTime": 0
            },
            {
                "startTime": 1477030973,
                "tagLink1": "mls\u003A\u002F\u002Fsearch\u002Fresult\u003Fkeyword\u003D\u53CA\u8E1D\u9774",
                "tagLink2": "",
                "tag2": "",
                "title": "\u624B\u5DE5\u76AE\u4E24\u7A7F\u9AD8\u8DDF\u53CA\u8E1D\u9774",
                "tagLink3": "",
                "tag3": "",
                "acm": "3.mce.2_10_1854q.9439.0.pTuq64sDy0W.m_189921_11228",
                "description": "\u8DDF\u9AD85cm\u3002\u53EF\u4E24\u7A7F\uFF0C\u6CA1\u6709\u52A0\u7ED2\uFF0C\u8FD9\u4E2A\u5B63\u8282\u7A7F\u521A\u521A\u597D\u3002",
                "link": "http\u003A\u002F\u002Fitem.meilishuo.com\u002Fh5\u002Fdetail\u002F1gp9z5o\u003Fmt\u003D12.9439.r189921.11228\u0026acm\u003D3.mce.2_10_1854q.9439.0.pTuq64sDy0W.m_189921_11228",
                "popularStar": "5",
                "image": "http\u003A\u002F\u002Fs7.mogucdn.com\u002Fp2\u002F161009\u002F1sp_33fl2eb62c044d88b3k329i1febdf_400x400.jpg",
                "endTime": 0,
                "tag1": "\u53CA\u8E1D\u9774"
            },
            {
                "tags": "\u58A8\u955C",
                "startTime": 1466154319,
                "title": "\u5E15\u838E\u58A8\u955C2016\u592A\u9633\u955C\u5706\u8138\u590D\u53E4\u8303",
                "acm": "3.mce.2_10_14ip8.5514.0.pTuq64sDy0X.m_105402_11228",
                "description": "\u8303\u51B0\u51B0\u4EE3\u8A00\u0020\u8D85\u8F7B\u6750\u8D28\u0020\u9632UV400\u0020\u70AB\u5F69\u65F6\u5C1A",
                "link": "http\u003A\u002F\u002Fsgitem.meilishuo.com\u002Fsgdetail\u002F650500031\u003Fmt\u003D12.5514.r105402.11228\u0026acm\u003D3.mce.2_10_14ip8.5514.0.pTuq64sDy0X.m_105402_11228",
                "popularStar": "5",
                "image": "http\u003A\u002F\u002Fs6.mogucdn.com\u002Fp1\u002F160511\u002F1vh_ifrdiyrugzrwenjxhazdambqmeyde_320x320.png",
                "endTime": 0
            },
            {
                "startTime": 1477030973,
                "tagLink1": "mls\u003A\u002F\u002Fsearch\u002Fresult\u003Fkeyword\u003D\u7CFB\u5E26",
                "title": "\u5706\u5934\u5E05\u6C14\u77ED\u9774",
                "tag2": "",
                "tagLink2": "",
                "tag3": "",
                "tagLink3": "",
                "acm": "3.mce.2_10_1854s.9439.0.pTuq64sDy0Y.m_189922_11228",
                "description": "\u65B0\u6B3E\u5E05\u6C14\u77ED\u9774\uFF0C\u5934\u5C42\u725B\u76AE\u6750\u8D28\uFF0C\u65F6\u5C1A\u9A7C\u8272\u548C\u767E\u642D\u9ED1\u8272\u4E24\u8272\u53EF\u9009\uFF0C\u505A\u5DE5\u975E\u5E38\u7684\u597D\uFF0C\u53EF\u4EE5\u7A7F\u5F88\u4E45\u54E6",
                "link": "http\u003A\u002F\u002Fitem.meilishuo.com\u002Fh5\u002Fdetail\u002F1gm1rs0\u003Fmt\u003D12.9439.r189922.11228\u0026acm\u003D3.mce.2_10_1854s.9439.0.pTuq64sDy0Y.m_189922_11228",
                "image": "http\u003A\u002F\u002Fs7.mogucdn.com\u002Fp2\u002F161009\u002F1sp_2j2jij6cfi89jeh6fcl7d1l8j37g4_400x400.jpg",
                "popularStar": "5",
                "endTime": 0,
                "tag1": "\u7CFB\u5E26"
            },
            {
                "startTime": 1477030973,
                "tagLink1": "mls\u003A\u002F\u002Fsearch\u002Fresult\u003Fkeyword\u003D\u80CC\u5E26\u88D9",
                "title": "\u7EA2\u8272\u65E0\u8896\u8FDE\u8863\u88D9",
                "tag2": "\u7CD6\u529B",
                "tagLink2": "mls\u003A\u002F\u002Fsearch\u002Fresult\u003Fkeyword\u003D\u7CD6\u529B",
                "tag3": "",
                "tagLink3": "",
                "acm": "3.mce.2_10_1854y.9439.0.pTuq64sDy0Z.m_189925_11228",
                "description": "\u51AC\u5929\u7A7F\u88D9\u5B50\u4F3C\u4E4E\u90FD\u6210\u4E86\u5962\u671B,\u6CA1\u5173\u7CFB\u8DDF\u7740\u5927\u5BB6\u4E00\u8D77Zuo\uFF0C\u80CC\u5E26\u88D9\u5FC5\u7136\u662F\u4F60\u7684\u9996\u8981\u9009\u62E9\u4E4B\u4E00\u3002",
                "link": "http\u003A\u002F\u002Fitem.meilishuo.com\u002Fh5\u002Fdetail\u002F1gp5wk6\u003Fmt\u003D12.9439.r189925.11228\u0026acm\u003D3.mce.2_10_1854y.9439.0.pTuq64sDy0Z.m_189925_11228",
                "image": "http\u003A\u002F\u002Fs7.mogucdn.com\u002Fp2\u002F161010\u002F1sd_4kckd026e74cc3bbeck86ba56hi17_400x400.jpg",
                "popularStar": "5",
                "endTime": 0,
                "tag1": "\u80CC\u5E26\u88D9"
            },
            {
                "startTime": 1477030973,
                "tagLink1": "mls\u003A\u002F\u002Fsearch\u002Fresult\u003Fkeyword\u003D\u62FC\u63A5",
                "title": "\u5C0F\u718A\u73A9\u5076\u5E73\u5E95\u978B",
                "tag2": "",
                "tagLink2": "",
                "tag3": "",
                "tagLink3": "",
                "acm": "3.mce.2_10_18550.9439.0.pTuq64sDy00.m_189926_11228",
                "description": "\u65B0\u51AC\u65B0\u6B3E\u5355\u978B\uFF0C\u897F\u65BD\u7ED2\u002B\u514D\u6BDB\u62FC\u63A5\uFF0C\u597D\u8F6F\u7684\u611F\u89C9\uFF0C\u5C0F\u718A\u73A9\u5076\u88C5\u9970\uFF0C\u53EF\u7231\u5973\u4EBA\u007E\u007E\u007E",
                "link": "http\u003A\u002F\u002Fitem.meilishuo.com\u002Fh5\u002Fdetail\u002F1gp60ig\u003Fmt\u003D12.9439.r189926.11228\u0026acm\u003D3.mce.2_10_18550.9439.0.pTuq64sDy00.m_189926_11228",
                "image": "http\u003A\u002F\u002Fs10.mogucdn.com\u002Fp2\u002F161009\u002F1sp_3b70lkc836j11eilc88953fde21ca_400x400.jpg",
                "popularStar": "5",
                "endTime": 0,
                "tag1": "\u62FC\u63A5"
            },
            {
                "startTime": 1477030974,
                "tagLink1": "mls\u003A\u002F\u002Fcategory\u002Fwall\u003Ffcid\u003D10057179\u0026title\u003D\u624B\u62FF\u5305\u0026mt\u003D12.5644.r92315.6051\u00A0",
                "title": "\u590D\u53E4\u624B\u62FF\u5305",
                "tag2": "",
                "tagLink2": "",
                "tag3": "",
                "tagLink3": "",
                "acm": "3.mce.2_10_18554.9439.0.pTuq64sDy01.m_189928_11228",
                "description": "\u8D85\u767E\u642D\u7684\u4E00\u6B3E\uFF0C\u624B\u62FF\u975E\u5E38\u6709\u8303\uFF0C\u800C\u4E14\u5305\u5305\u914D\u6709\u957F\u80A9\u5E26\uFF0C\u53EF\u4EE5\u5355\u80A9\u659C\u630E\u4F7F\u7528",
                "link": "http\u003A\u002F\u002Fitem.meilishuo.com\u002Fh5\u002Fdetail\u002F1fs156u\u003Fmt\u003D12.9439.r189928.11228\u0026acm\u003D3.mce.2_10_18554.9439.0.pTuq64sDy01.m_189928_11228",
                "image": "http\u003A\u002F\u002Fs6.mogucdn.com\u002Fp2\u002F160825\u002F1s6_25h1flk41416e61cgi48k93e472l7_400x400.jpg",
                "popularStar": "5",
                "endTime": 0,
                "tag1": "\u624B\u62FF\u5305"
            },
            {
                "startTime": 1477030974,
                "tagLink1": "mls\u003A\u002F\u002Fsearch\u002Fresult\u003Fkeyword\u003D\u9488\u7EC7\u5F00\u886B",
                "tagLink2": "",
                "tag2": "",
                "title": "\u7EAF\u8272\u6BDB\u8863\u5916\u5957",
                "tagLink3": "",
                "tag3": "",
                "acm": "3.mce.2_10_1855i.9439.0.pTuq64sDy02.m_189935_11228",
                "description": "\u5F00\u886B\u672C\u8EAB\u5B9E\u7A7F\u5EA6\u5C31\u5F88\u9AD8\uFF0C\u6311\u9009\u6709\u65F6\u9AE6\u611F\u7684\u5F00\u886B\uFF0C\u7EB1\u7EBF\u8868\u73B0\u529B\u662F\u91CD\u70B9\uFF0C\u65E5\u672C\u8FDB\u53E3\u7EB1\uFF0C\u7F8A\u9A7C\u7F8A\u6BDB\u6DF7\u7EBA\u7EB1\uFF0C\u957F\u6BDB\u7684\u6548\u679C\u5F88\u6709\u6175\u61D2\u611F\uFF0C\u5177\u6709\u51CF\u9F84\u6548\u679C\u54E6\uFF01",
                "link": "http\u003A\u002F\u002Fitem.meilishuo.com\u002Fh5\u002Fdetail\u002F1glu54c\u003Fmt\u003D12.9439.r189935.11228\u0026acm\u003D3.mce.2_10_1855i.9439.0.pTuq64sDy02.m_189935_11228",
                "popularStar": "4",
                "image": "http\u003A\u002F\u002Fs7.mogucdn.com\u002Fp2\u002F160905\u002F1sd_5k60ej569110hldcgl12i74j76b3e_400x400.jpg",
                "endTime": 0,
                "tag1": "\u9488\u7EC7\u5F00\u886B"
            },
            {
                "startTime": 1477030974,
                "tagLink1": "mls\u003A\u002F\u002Fsearch\u002Fresult\u003Fkeyword\u003D\u6263\u88A2",
                "tagLink2": "",
                "tag2": "",
                "title": "\u7C97\u8DDF\u5207\u5C14\u897F\u9774",
                "tagLink3": "",
                "tag3": "",
                "acm": "3.mce.2_10_18558.9439.0.pTuq64sDy03.m_189930_11228",
                "description": "\u53C8\u5230\u4E86\u7A7F\u9774\u5B50\u7684\u5B63\u8282\uFF0C\u59D1\u5A18\uFF0C\u4E70\u77ED\u9774\u4E86\u5417\uFF1F",
                "link": "http\u003A\u002F\u002Fitem.meilishuo.com\u002Fh5\u002Fdetail\u002F1gm3i9q\u003Fmt\u003D12.9439.r189930.11228\u0026acm\u003D3.mce.2_10_18558.9439.0.pTuq64sDy03.m_189930_11228",
                "popularStar": "5",
                "image": "http\u003A\u002F\u002Fs8.mogucdn.com\u002Fp2\u002F160829\u002F1sp_43d7k71i74blg9e609g06f1477c0b_400x400.jpg",
                "endTime": 0,
                "tag1": "\u6263\u88A2"
            },
            {
                "startTime": 1477030974,
                "tagLink1": "mls\u003A\u002F\u002Fsearch\u002Fresult\u003Fkeyword\u003D\u536B\u8863",
                "tagLink2": "",
                "tag2": "",
                "title": "\u4F11\u95F2\u649E\u8272\u79CB\u88C5\u536B\u8863",
                "tagLink3": "",
                "tag3": "",
                "acm": "3.mce.2_10_1855a.9439.0.pTuq64sDy04.m_189931_11228",
                "description": "\u5BBD\u677E\u4E2D\u56FD\u98CE\u5370\u82B1\u4E0A\u8863\uFF0C\u4E2D\u56FD\u98CE\u5FBD\u7AE0\u523A\u7EE3\uFF0C\u8BA9\u4F60\u611F\u53D7\u4E0D\u4E00\u6837\u7684\u6F6Efeel\u007E",
                "link": "http\u003A\u002F\u002Fitem.meilishuo.com\u002Fh5\u002Fdetail\u002F1gl98wg\u003Fmt\u003D12.9439.r189931.11228\u0026acm\u003D3.mce.2_10_1855a.9439.0.pTuq64sDy04.m_189931_11228",
                "popularStar": "4",
                "image": "http\u003A\u002F\u002Fs7.mogucdn.com\u002Fp2\u002F160825\u002F1s3_4fedigefcdc02ifh1lcibl75d2f3b_400x400.jpg",
                "endTime": 0,
                "tag1": "\u536B\u8863"
            },
            {
                "startTime": 1477030974,
                "tagLink1": "mls\u003A\u002F\u002Fsearch\u002Fresult\u003Fkeyword\u003D\u536B\u8863",
                "tagLink2": "mls\u003A\u002F\u002Fsearch\u002Fresult\u003Fkeyword\u003D\u649E\u8272",
                "tag2": "\u649E\u8272",
                "title": "\u649E\u8272\u60C5\u4FA3\u536B\u8863",
                "tagLink3": "mls\u003A\u002F\u002Fsearch\u002Fresult\u003Fkeyword\u003D\u60C5\u4FA3\u88C5",
                "tag3": "\u60C5\u4FA3\u88C5",
                "acm": "3.mce.2_10_1855e.9439.0.pTuq64sDy05.m_189933_11228",
                "description": "\u80F8\u524D\u7684\u649E\u8272\u5B57\u6BCD\u8D34\u5E03\uFF0C\u539F\u5BBF\u8857\u5934\u5473\u9053\u007E\u007E\u6311\u9009\u4E86\u9002\u5408\u60C5\u4FA3\u7A7F\u7684\u51E0\u4E2A\u989C\u8272\u007E\u4E00\u8D77\u51FA\u8857\u4EC0\u4E48\u7684\uFF0C\u8FD8\u662F\u5F88\u60F9\u4EBA\u7FA1\u6155\u6EF4\u007E\u007E",
                "link": "http\u003A\u002F\u002Fitem.meilishuo.com\u002Fh5\u002Fdetail\u002F1gle0ms\u003Fmt\u003D12.9439.r189933.11228\u0026acm\u003D3.mce.2_10_1855e.9439.0.pTuq64sDy05.m_189933_11228",
                "popularStar": "5",
                "image": "http\u003A\u002F\u002Fs7.mogucdn.com\u002Fp2\u002F160831\u002F1sd_83d6k1693fac10chf5055kd6ia58d_400x400.jpg",
                "endTime": 0,
                "tag1": "\u536B\u8863"
            },
            {
                "startTime": 1477030974,
                "tagLink1": "mls\u003A\u002F\u002Fsearch\u002Fresult\u003Fkeyword\u003D\u9488\u7EC7",
                "tagLink2": "mls\u003A\u002F\u002Fsearch\u002Fresult\u003Fkeyword\u003D\u8FDE\u8863\u88D9",
                "tag2": "\u8FDE\u8863\u88D9",
                "title": "\u9AD8\u9886\u9488\u7EC7\u8FDE\u8863\u88D9",
                "tagLink3": "",
                "tag3": "",
                "acm": "3.mce.2_10_1855g.9439.0.pTuq64sDy06.m_189934_11228",
                "description": "\u88F8\u8272\u5C3D\u60C5\u5730\u6563\u53D1\u7740\u67D4\u548C\u4E4B\u611F,\u7EC6\u5FAE\u7684\u9AD8\u9886\u8BBE\u8BA1\u4E5F\u4E3A\u9020\u578B\u589E\u6DFB\u4E86\u4E00\u4E1D\u9AD8\u96C5,\u6253\u9020\u51FA\u4E86\u81EA\u7136\u597D\u6C14\u8272\u3002",
                "link": "http\u003A\u002F\u002Fitem.meilishuo.com\u002Fh5\u002Fdetail\u002F1glvhu6\u003Fmt\u003D12.9439.r189934.11228\u0026acm\u003D3.mce.2_10_1855g.9439.0.pTuq64sDy06.m_189934_11228",
                "popularStar": "5",
                "image": "http\u003A\u002F\u002Fs10.mogucdn.com\u002Fp2\u002F160906\u002F1s3_58ike65ka1dihi80f33a6h1cci958_400x400.jpg",
                "endTime": 0,
                "tag1": "\u9488\u7EC7"
            },
            {
                "startTime": 1477030973,
                "tagLink1": "mls\u003A\u002F\u002Fsearch\u002Fresult\u003Fkeyword\u003D\u8367\u5149",
                "title": "\u9A6C\u6BDB\u9AD8\u8DDF\u77ED\u9774\u53CA\u8E1D\u9774",
                "tag2": "",
                "tagLink2": "",
                "tag3": "",
                "tagLink3": "",
                "acm": "3.mce.2_10_1854k.9439.0.pTuq64sDy07.m_189918_11228",
                "description": "\u5C0F\u7EFF\u9A9A\u6C14\u5417\uFF1F\u642D\u914D\u9A6C\u6BDB\u6750\u8D28\uFF0C\u8D5A\u8DB3\u56DE\u5934\u7387\u3002\u7ED9\u8FD9\u4E2A\u79CB\u5929\u52A0\u70B9\u989C\u8272\uFF01",
                "link": "http\u003A\u002F\u002Fitem.meilishuo.com\u002Fh5\u002Fdetail\u002F1go2akk\u003Fmt\u003D12.9439.r189918.11228\u0026acm\u003D3.mce.2_10_1854k.9439.0.pTuq64sDy07.m_189918_11228",
                "image": "http\u003A\u002F\u002Fs6.mogucdn.com\u002Fp2\u002F161010\u002F1sp_49ccba20f7ea55alj4c768f58b639_400x400.jpg",
                "popularStar": "5",
                "endTime": 0,
                "tag1": "\u8367\u5149"
            }
        ],
        "nextPage": 3
    },
    "returnCode": "SUCCESS",
    "success": true
}